{"cameraMode":{"drawMode":0,"name":"Shaded","section":"Shading Mode"},"sceneLighting":true,"audioPlay":false,"sceneViewState":{"showFog":true,"showMaterialUpdate":false,"showSkybox":true,"showFlares":true,"showImageEffects":true,"showParticleSystems":true},"in2DMode":false,"pivot":{"x":1.8493638038635255,"y":7.23141622543335,"z":-0.4696800708770752},"rotation":{"x":-0.20181122422218324,"y":0.7826740741729736,"z":-0.31926295161247256,"w":-0.49473923444747927},"size":4.206876754760742,"orthographic":false}